omfcore
