Metadata-Version: 1.1
Name: organize-media-files
Version: 1.0.1
Summary: Organize Media Files
Home-page: https://github.com/IsaacMother/organize-media-files
Author: Andrey Turbov
Author-email: andrey.turbov@gmail.com
License: GPL-3
Keywords: music collection pranizer
Platform: all
Classifier: Development Status :: 4 - Beta
Classifier: Environment :: Console
Classifier: Intended Audience :: Developers
Classifier: License :: Other/Proprietary License
Classifier: Natural Language :: English
Classifier: Operating System :: OS Independent
Classifier: Programming Language :: Python :: 3.5
Classifier: Topic :: Multimedia :: Sound/Audio
Classifier: Topic :: Utilities
